openeo_r_udf/__init__.py
openeo_r_udf/executor.R
openeo_r_udf/udf_lib.py
openeo_r_udf-0.5.0.dist-info/METADATA
openeo_r_udf-0.5.0.dist-info/WHEEL
openeo_r_udf-0.5.0.dist-info/top_level.txt
openeo_r_udf-0.5.0.dist-info/RECORD
