Metadata-Version: 2.1
Name: openeo-r-udf
Version: 0.5.0
Summary: Run openEO R UDFs from Python
Home-page: https://github.com/Open-EO/openeo-udf-python-to-r
Author: Matthias Mohr
Author-email: m.mohr@uni-muenster.de
Project-URL: Issues, https://github.com/Open-EO/openeo-udf-python-to-r/issues
Keywords: openeo,r,udf,python
Classifier: Development Status :: 4 - Beta
Classifier: License :: OSI Approved :: Apache Software License
Classifier: Programming Language :: Python :: 3.7
Classifier: Programming Language :: Python :: 3.8
Classifier: Programming Language :: Python :: 3.9
Classifier: Programming Language :: Python :: 3.10
Classifier: Programming Language :: Python :: 3.11
Requires-Dist: requests
Requires-Dist: numpy
Requires-Dist: xarray
Requires-Dist: rpy2
Provides-Extra: parallel
Requires-Dist: joblib ; extra == 'parallel'
